s3utils/__init__.py
s3utils/s3utils.py
s3utils-0.6.1.dist-info/DESCRIPTION.rst
s3utils-0.6.1.dist-info/METADATA
s3utils-0.6.1.dist-info/metadata.json
s3utils-0.6.1.dist-info/pbr.json
s3utils-0.6.1.dist-info/RECORD
s3utils-0.6.1.dist-info/top_level.txt
s3utils-0.6.1.dist-info/WHEEL
