Metadata-Version: 1.1
Name: s3utils
Version: 0.6.1
Summary: S3 Utils deals with Amazon S3 buckets
Home-page: https://github.com/seperman/s3utils
Author: Seperman
Author-email: sep@zepworks.com
License: Apache License 2.0
Download-URL: https://github.com/seperman/s3utils/tarball/master
Platform: UNKNOWN
Classifier: Environment :: Web Environment
Classifier: Intended Audience :: Developers
Classifier: Operating System :: OS Independent
Classifier: Topic :: Software Development
Classifier: Programming Language :: Python :: 2.7
Classifier: Programming Language :: Python :: 3.3
Classifier: Programming Language :: Python :: 3.4
Classifier: Programming Language :: Python :: 3.5
Classifier: Topic :: Internet :: WWW/HTTP
Classifier: Topic :: Internet :: WWW/HTTP :: Dynamic Content
Classifier: License :: OSI Approved :: Apache Software License
